{"cameraMode":{"drawMode":0,"name":"Shaded","section":"Shading Mode"},"sceneLighting":true,"audioPlay":false,"sceneViewState":{"m_AlwaysRefresh":false,"showFog":true,"showSkybox":true,"showFlares":true,"showImageEffects":true,"showParticleSystems":true,"showVisualEffectGraphs":true,"m_FxEnabled":true},"in2DMode":false,"pivot":{"x":-964.0516357421875,"y":-263.82763671875,"z":1600.580810546875},"rotation":{"x":0.06804221123456955,"y":-0.27298447489738467,"z":0.019409973174333574,"w":0.9595032334327698},"size":947.48046875,"orthographic":false}