{"cameraMode":{"drawMode":0,"name":"Shaded","section":"Shading Mode"},"sceneLighting":true,"audioPlay":false,"sceneViewState":{"m_AlwaysRefresh":false,"showFog":true,"showSkybox":true,"showFlares":true,"showImageEffects":true,"showParticleSystems":true,"showVisualEffectGraphs":true,"m_FxEnabled":true},"in2DMode":false,"pivot":{"x":-43.85382080078125,"y":5.463018894195557,"z":9.249171257019043},"rotation":{"x":-0.10047885775566101,"y":-0.6849310398101807,"z":0.0965801402926445,"w":-0.7152757048606873},"size":1.2786387205123902,"orthographic":false}